redis_message_queue/__init__.py
redis_message_queue/_abstract_redis_gateway.py
redis_message_queue/_config.py
redis_message_queue/_queue_key_manager.py
redis_message_queue/_redis_gateway.py
redis_message_queue/asyncio/__init__.py
redis_message_queue/asyncio/_abstract_redis_gateway.py
redis_message_queue/asyncio/_redis_gateway.py
redis_message_queue/asyncio/redis_message_queue.py
redis_message_queue/interrupt_handler/__init__.py
redis_message_queue/interrupt_handler/_implementation.py
redis_message_queue/interrupt_handler/_interface.py
redis_message_queue/redis_message_queue.py
redis_message_queue-0.10.1.dist-info/LICENSE
redis_message_queue-0.10.1.dist-info/METADATA
redis_message_queue-0.10.1.dist-info/WHEEL
redis_message_queue-0.10.1.dist-info/RECORD
