Metadata-Version: 2.1
Name: redis-message-queue
Version: 0.10.1
Summary: Python message queuing with Redis and message deduplication
Author: Elijas
Author-email: 4084885+Elijas@users.noreply.github.com
Requires-Python: >=3.8,<4.0
Classifier: Programming Language :: Python :: 3
Classifier: Programming Language :: Python :: 3.8
Classifier: Programming Language :: Python :: 3.9
Classifier: Programming Language :: Python :: 3.10
Classifier: Programming Language :: Python :: 3.11
Requires-Dist: redis
Requires-Dist: tenacity
